[
  {
    "title": "Matcha Cheesecake",
    "categories": [
      "cake",
      "dessert"
    ],
    "activeTime": 30,
    "passiveTime": 240,
    "totalTime": 270,
    "servings": 8,
    "difficulty": "easy",
    "originality": 5,
    "taste": 5,
    "status": "noPicture",
    "ingredients": [
      {
        "name": "butter cookies",
        "amount": 100,
        "unit": "g"
      },
      {
        "name": "butter",
        "amount": 60,
        "unit": "g"
      },
      {
        "name": "cream cheese (double cream)",
        "amount": 250,
        "unit": "g"
      },
      {
        "name": "whip cream",
        "amount": 200,
        "unit": "g"
      },
      {
        "name": "yogurt",
        "amount": 50,
        "unit": "g"
      },
      {
        "name": "sugar",
        "amount": 60,
        "unit": "g"
      },
      {
        "name": "gelatin sheets",
        "amount": 1.5,
        "unit": "sheets"
      },
      {
        "name": "vanilla extract (alternatively vanilla paste)",
        "amount": 1,
        "unit": "dash"
      },
      {
        "name": "matcha powder",
        "amount": 7,
        "unit": "g"
      },
      {
        "name": "milk (hot)",
        "amount": 30,
        "unit": "ml"
      }
    ],
    "image": "https://ik.imagekit.io/o9fejv2tr/Food%20Images/MatchaCheesecake.jpg?updatedAt=1756588930033",
    "file": "recipes/cakesAndPastries/MatchaCheesecake.html"
  },
  {
    "title": "Chicken Stock",
    "categories": [
      "component",
      "basics"
    ],
    "activeTime": 1,
    "passiveTime": 60,
    "totalTime": 61,
    "servings": 2,
    "difficulty": "easy",
    "originality": 5,
    "taste": 5,
    "status": "done",
    "source": "Mama",
    "ingredients": [
      {
        "name": "chicken bones",
        "amount": 500,
        "unit": "g"
      },
      {
        "name": "water",
        "amount": 1,
        "unit": "l"
      },
      {
        "name": "salt",
        "amount": 1,
        "unit": "tsp"
      },
      {
        "name": "chicken bouillon powder",
        "amount": 1,
        "unit": "tsp"
      },
      {
        "name": "onion",
        "amount": 0.5,
        "unit": "piece"
      },
      {
        "name": "ginger"
      }
    ],
    "image": "https://ik.imagekit.io/o9fejv2tr/Food%20Images/ChickenBroth.jpg?updatedAt=1756588700258",
    "file": "recipes/component/ChickenStock.html"
  },
  {
    "title": "Mongolian Ground Beef",
    "categories": [
      "Mongolia",
      "Beef"
    ],
    "activeTime": 5,
    "passiveTime": 15,
    "totalTime": 20,
    "servings": 3,
    "difficulty": "easy",
    "originality": 1,
    "taste": 5,
    "status": "done",
    "source": "https://youtu.be/ImEDbyWuswU?si=VzX9VNzUFgjhMOP4",
    "ingredients": [
      {
        "name": "spring onions",
        "amount": 5,
        "unit": "pcs"
      },
      {
        "name": "garlic",
        "amount": 3,
        "unit": "cloves"
      },
      {
        "name": "ginger (grated)",
        "amount": 2.5,
        "unit": "tsp"
      },
      {
        "name": "oil"
      },
      {
        "name": "ground beef",
        "amount": 500,
        "unit": "g"
      },
      {
        "name": "chili",
        "amount": 1,
        "unit": "pcs"
      },
      {
        "name": "sesame oil (toasted)",
        "amount": 0.5,
        "unit": "tbsp"
      },
      {
        "name": "soy sauce (light)",
        "amount": 3,
        "unit": "tbsp"
      },
      {
        "name": "sugar",
        "amount": 2,
        "unit": "tbsp"
      },
      {
        "name": "oyster sauce",
        "amount": 1,
        "unit": "tbsp"
      },
      {
        "name": "chicken bouillon powder",
        "amount": 1,
        "unit": "tsp"
      },
      {
        "name": "soy sauce (dark)",
        "amount": 0.5,
        "unit": "tsp"
      },
      {
        "name": "light corn syrum (alternatively honey)",
        "amount": 1,
        "unit": "tbsp"
      },
      {
        "name": "Shaoxing wine (alternatively mirin)",
        "amount": 2,
        "unit": "tbsp"
      },
      {
        "name": "pepper (black)"
      },
      {
        "name": "water",
        "amount": 5,
        "unit": "tbsp"
      },
      {
        "name": "cornstarch",
        "amount": 1,
        "unit": "tbsp"
      }
    ],
    "image": "https://ik.imagekit.io/o9fejv2tr/Food%20Images/MongolianBeef.jpg?updatedAt=1756588943307",
    "file": "recipes/beef/MongolianGroundBeef.html"
  },
  {
    "title": "Currywurst",
    "categories": [
      "Germany",
      "Streetfood"
    ],
    "activeTime": 10,
    "passiveTime": 10,
    "totalTime": 20,
    "servings": 2,
    "difficulty": "easy",
    "originality": 4,
    "taste": 5,
    "status": "done",
    "source": "https://youtu.be/b3LKBp3KliQ?si=_Vcg0deSep1rEIGH",
    "ingredients": [
      {
        "name": "bratwurst",
        "amount": 2,
        "unit": "pcs"
      },
      {
        "name": "bell pepper (red)",
        "amount": 0.5,
        "unit": "pcs"
      },
      {
        "name": "onion (white)",
        "amount": 1,
        "unit": "pcs"
      },
      {
        "name": "orange juice",
        "amount": 250,
        "unit": "ml"
      },
      {
        "name": "cola",
        "amount": 100,
        "unit": "ml"
      },
      {
        "name": "ketchup",
        "amount": 650,
        "unit": "g"
      },
      {
        "name": "curry powder",
        "amount": 2,
        "unit": "tbsp"
      }
    ],
    "image": "https://ik.imagekit.io/o9fejv2tr/Food%20Images/CurryWurst.jpg?updatedAt=1756588725175",
    "file": "recipes/streetfood/Currywurst.html"
  },
  {
    "title": "Bánh Dầy",
    "categories": [
      "Vietnam",
      "Streetfood"
    ],
    "activeTime": 25,
    "passiveTime": 85,
    "totalTime": 110,
    "servings": 8,
    "difficulty": "medium",
    "originality": 5,
    "taste": 5,
    "status": "done",
    "source": "https://youtu.be/4QVaSE9v7RE?si=PeXVB_3-8X5oNiEV",
    "ingredients": [
      {
        "name": "glutinous rice flour",
        "amount": 200,
        "unit": "g"
      },
      {
        "name": "salt",
        "amount": 0.5,
        "unit": "tsp"
      },
      {
        "name": "water (boiled)",
        "amount": 100,
        "unit": "ml"
      },
      {
        "name": "vegetable oil",
        "amount": 0.66,
        "unit": "tbsp"
      },
      {
        "name": "water",
        "amount": 60,
        "unit": "ml"
      },
      {
        "name": "giò"
      }
    ],
    "image": "https://ik.imagekit.io/o9fejv2tr/Food%20Images/BanhGiay.jpg?updatedAt=1757778203905",
    "file": "recipes/streetfood/BanhDay.html"
  },
  {
    "title": "Gurkensalat",
    "categories": [
      "vegetables",
      "vegan",
      "vegetarian",
      "salad",
      "Germany"
    ],
    "activeTime": 15,
    "passiveTime": 20,
    "totalTime": 35,
    "servings": 2,
    "difficulty": "easy",
    "originality": 5,
    "taste": 5,
    "status": "done",
    "source": "https://youtu.be/bJLRYT3iqmo?si=nqtuF5TSzZ583xlt",
    "ingredients": [
      {
        "name": "cucumber",
        "amount": 1,
        "unit": "pcs"
      },
      {
        "name": "salt"
      },
      {
        "name": "pepper"
      },
      {
        "name": "sugar",
        "amount": 1,
        "unit": "tsp"
      },
      {
        "name": "onion",
        "amount": 0.5,
        "unit": "pcs"
      },
      {
        "name": "dill",
        "amount": 1,
        "unit": "tbsp"
      },
      {
        "name": "apple vinegar",
        "amount": 2,
        "unit": "tbsp"
      },
      {
        "name": "vegetable oil",
        "amount": 1,
        "unit": "tbsp"
      }
    ],
    "image": "https://ik.imagekit.io/o9fejv2tr/Food%20Images/Gurkensalat.jpg?updatedAt=1756588883075",
    "file": "recipes/vegetables/Gurkensalat.html"
  },
  {
    "title": "Rahmspinat",
    "categories": [
      "Germany",
      "vegetables",
      "vegetarian"
    ],
    "activeTime": 25,
    "passiveTime": 10,
    "totalTime": 35,
    "servings": 4,
    "difficulty": "easy",
    "originality": 5,
    "taste": 5,
    "status": "done",
    "source": "https://youtu.be/vbhtBPLlgUA?si=yIP44M-r0w1DAz78",
    "ingredients": [
      {
        "name": "spinach leaves",
        "amount": 400,
        "unit": "g"
      },
      {
        "name": "shallots",
        "amount": 2,
        "unit": "pcs"
      },
      {
        "name": "garlic",
        "amount": 1,
        "unit": "clove"
      },
      {
        "name": "butter"
      },
      {
        "name": "cream",
        "amount": 500,
        "unit": "ml"
      },
      {
        "name": "salt"
      },
      {
        "name": "pepper"
      },
      {
        "name": "nutmeg"
      }
    ],
    "image": "https://ik.imagekit.io/o9fejv2tr/Food%20Images/Rahmspinat.jpg?updatedAt=1756588974344",
    "file": "recipes/vegetables/Rahmspinat.html"
  },
  {
    "title": "Pandan Jelly",
    "categories": [
      "component",
      "vegan",
      "vegetarian"
    ],
    "activeTime": 15,
    "passiveTime": 75,
    "totalTime": 90,
    "servings": 10,
    "difficulty": "easy",
    "originality": 5,
    "taste": 4,
    "status": "done",
    "source": "https://youtu.be/7C6Bj4f2Yv0?si=BuEW8ELRYq6RjA16",
    "ingredients": [
      {
        "name": "agar agar",
        "amount": 10,
        "unit": "g"
      },
      {
        "name": "sugar",
        "amount": 100,
        "unit": "g"
      },
      {
        "name": "pandan leave (alternatively: pandan extract)",
        "amount": 3,
        "unit": "pcs"
      },
      {
        "name": "water",
        "amount": 100,
        "unit": "ml"
      },
      {
        "name": "water",
        "amount": 900,
        "unit": "ml"
      },
      {
        "name": "salt",
        "amount": 1,
        "unit": "pinch"
      }
    ],
    "image": "https://ik.imagekit.io/o9fejv2tr/Food%20Images/ThachLaDua.jpg?updatedAt=1757778312983",
    "file": "recipes/component/PandanJelly.html"
  },
  {
    "title": "Hạt lựu",
    "categories": [
      "component",
      "vegan",
      "vegetarian"
    ],
    "activeTime": 20,
    "passiveTime": 15,
    "totalTime": 35,
    "servings": 2,
    "difficulty": "easy",
    "originality": 5,
    "taste": 5,
    "status": "needPic",
    "source": "https://youtu.be/7C6Bj4f2Yv0?si=BuEW8ELRYq6RjA16",
    "ingredients": [
      {
        "name": "water chestnuts",
        "amount": 150,
        "unit": "g"
      },
      {
        "name": "food coloring (red)",
        "amount": 1,
        "unit": "tsp"
      },
      {
        "name": "water",
        "amount": 1,
        "unit": "tsp"
      },
      {
        "name": "tapioca starch",
        "amount": 100,
        "unit": "g"
      },
      {
        "name": "lychee syrup",
        "amount": 1,
        "unit": "tbsp"
      },
      {
        "name": "toddy palm seed syrup",
        "amount": 1,
        "unit": "tbsp"
      }
    ],
    "image": "https://ik.imagekit.io/o9fejv2tr/Food%20Images/HatLuu.jpg",
    "file": "recipes/component/HatLuu.html"
  },
  {
    "title": "Aioli",
    "categories": [
      "sauce",
      "Spain"
    ],
    "activeTime": 10,
    "passiveTime": 0,
    "totalTime": 10,
    "servings": 2,
    "difficulty": "easy",
    "originality": 5,
    "taste": 5,
    "status": "done",
    "source": "https://youtu.be/p3Xb9aPwpdc?si=V6zDGSpHpo3_wKgw",
    "ingredients": [
      {
        "name": "garlic",
        "amount": 4,
        "unit": "cloves"
      },
      {
        "name": "whole milk",
        "amount": 70,
        "unit": "ml"
      },
      {
        "name": "salt"
      },
      {
        "name": "(sunflower) oil",
        "amount": 100,
        "unit": "ml"
      },
      {
        "name": "olive oil (alternatively sunflower oil)",
        "amount": 50,
        "unit": "ml"
      }
    ],
    "image": "https://ik.imagekit.io/o9fejv2tr/Food%20Images/Aioli.jpg?updatedAt=1756588648469",
    "file": "recipes/dressings-dips-sauces/aioli.html"
  },
  {
    "title": "Nước chấm bún chả",
    "categories": [
      "Vietnam",
      "dressing"
    ],
    "activeTime": 5,
    "passiveTime": 5,
    "totalTime": 10,
    "servings": 3,
    "difficulty": "easy",
    "originality": 5,
    "taste": 5,
    "status": "done",
    "source": "https://youtu.be/SQ1j8WkOUZM?si=UXA1g7nha3cj3kf9",
    "ingredients": [
      {
        "name": "water",
        "amount": 300,
        "unit": "ml"
      },
      {
        "name": "sugar",
        "amount": 2.5,
        "unit": "tbsp"
      },
      {
        "name": "fish sauce",
        "amount": 3,
        "unit": "tbsp"
      },
      {
        "name": "vinegar",
        "amount": 0.66,
        "unit": "tbsp"
      }
    ],
    "image": "https://ik.imagekit.io/o9fejv2tr/Food%20Images/NuocChamBunCha.jpg?updatedAt=1757778248190",
    "file": "recipes/dressings-dips-sauces/NuocMamBunCha.html"
  },
  {
    "title": "Tomato sauce",
    "categories": [
      "sauce",
      "basics",
      "Italy",
      "vegan",
      "vegetarian"
    ],
    "activeTime": 20,
    "passiveTime": 30,
    "totalTime": 50,
    "servings": 2,
    "difficulty": "easy",
    "originality": 5,
    "taste": 5,
    "status": "done",
    "source": "https://youtu.be/tPfCZrk5mGY?si=gaPy5M-ARprWLw4P",
    "ingredients": [
      {
        "name": "water (boiled)"
      },
      {
        "name": "tomatoes",
        "amount": 1,
        "unit": "kg"
      },
      {
        "name": "onion",
        "amount": 1,
        "unit": "pcs"
      },
      {
        "name": "olive oil",
        "amount": 2,
        "unit": "tbsp"
      },
      {
        "name": "salt",
        "amount": 1,
        "unit": "tsp"
      },
      {
        "name": "sugar",
        "amount": 1,
        "unit": "tsp"
      },
      {
        "name": "basil leaves (fresh)"
      }
    ],
    "image": "https://ik.imagekit.io/o9fejv2tr/Food%20Images/TomatoSauce.jpg?updatedAt=1762116819362",
    "file": "recipes/dressings-dips-sauces/TomatoSauce.html"
  },
  {
    "title": "Sauce Hollandaise",
    "categories": [
      "sauce",
      "France",
      "vegetarian"
    ],
    "activeTime": 15,
    "passiveTime": 5,
    "totalTime": 20,
    "servings": 6,
    "difficulty": "easy",
    "originality": 5,
    "taste": 5,
    "status": "done",
    "source": "https://www.chefkoch.de/rezepte/232131094977348/Sauce-Hollandaise.html",
    "ingredients": [
      {
        "name": "butter",
        "amount": 250,
        "unit": "g"
      },
      {
        "name": "egg yolks",
        "amount": 3,
        "unit": "pcs"
      },
      {
        "name": "water",
        "amount": 3,
        "unit": "tbsp"
      },
      {
        "name": "lemon juice",
        "amount": 1,
        "unit": "tbsp"
      },
      {
        "name": "salt"
      },
      {
        "name": "pepper (white)"
      },
      {
        "name": "cayenne pepper"
      }
    ],
    "image": "https://ik.imagekit.io/o9fejv2tr/Food%20Images/SauceHollandaise.jpg?updatedAt=1762117727527",
    "file": "recipes/dressings-dips-sauces/SauceHollandaise.html"
  },
  {
    "title": "Microwave Potato Chips",
    "categories": [
      "snacks",
      "vegan",
      "vegetarian",
      "potato"
    ],
    "activeTime": 25,
    "passiveTime": 10,
    "totalTime": 35,
    "servings": 2,
    "difficulty": "easy",
    "originality": 2,
    "taste": 3,
    "status": "done",
    "source": "https://youtu.be/v514hwoC_fY?si=KxbEVOGPHW5EF2uw",
    "ingredients": [
      {
        "name": "potato (starchy)"
      },
      {
        "name": "oil"
      },
      {
        "name": "salt"
      }
    ],
    "image": "https://ik.imagekit.io/o9fejv2tr/Food%20Images/MicrowavePotatoChips.jpg?updatedAt=1762118197307",
    "file": "recipes/snacks/MicrowavePotatoChips.html"
  },
  {
    "title": "Pickled Vegetables (e.g. for Bún Chả)",
    "categories": [
      "vegan",
      "vegetarian",
      "vegetables",
      "basics"
    ],
    "activeTime": 15,
    "passiveTime": 180,
    "totalTime": 195,
    "servings": 6,
    "difficulty": "easy",
    "originality": 5,
    "taste": 4,
    "status": "needPic",
    "source": "https://youtu.be/SQ1j8WkOUZM?si=UXA1g7nha3cj3kf9",
    "ingredients": [
      {
        "name": "carrots",
        "amount": 100,
        "unit": "g"
      },
      {
        "name": "kohlrabi",
        "amount": 100,
        "unit": "g"
      },
      {
        "name": "salt",
        "amount": 1,
        "unit": "tsp"
      },
      {
        "name": "sugar",
        "amount": 2,
        "unit": "tbsp"
      },
      {
        "name": "vinegar",
        "amount": 2,
        "unit": "tbsp"
      },
      {
        "name": "water",
        "amount": 4,
        "unit": "tbsp"
      }
    ],
    "image": "https://ik.imagekit.io/o9fejv2tr/Food%20Images/PickledVegetables.jpg",
    "file": "recipes/vegetables/PickledVegetables.html"
  },
  {
    "title": "Cơm Hoàng Hậu",
    "categories": [
      "Vietnam",
      "rice",
      "chicken"
    ],
    "activeTime": 30,
    "passiveTime": 80,
    "totalTime": 110,
    "servings": 3,
    "difficulty": "easy",
    "originality": 5,
    "taste": 5,
    "status": "done",
    "source": "Mama",
    "ingredients": [
      {
        "name": "chicken tigh",
        "amount": 500,
        "unit": "g"
      },
      {
        "name": "fish sauce",
        "amount": 2,
        "unit": "tbsp"
      },
      {
        "name": "chicken bouillon powder",
        "amount": 1,
        "unit": "tsp"
      },
      {
        "name": "MSG",
        "amount": 1,
        "unit": "pinch"
      },
      {
        "name": "pepper"
      },
      {
        "name": "coriander"
      },
      {
        "name": "shiitake mushroom",
        "amount": 15,
        "unit": "pcs"
      },
      {
        "name": "onion",
        "amount": 1.5,
        "unit": "pcs"
      },
      {
        "name": "coconut oil"
      },
      {
        "name": "spring onion",
        "amount": 2,
        "unit": "pcs"
      },
      {
        "name": "rice",
        "amount": 2.5,
        "unit": "cups"
      },
      {
        "name": "coconut milk (optional)"
      }
    ],
    "image": "https://ik.imagekit.io/o9fejv2tr/Food%20Images/ComHoangHau.jpg?updatedAt=1756588717497",
    "file": "recipes/rice/ComHoangHau.html"
  },
  {
    "title": "Mexican Cilantro Rice",
    "categories": [
      "Mexico",
      "rice",
      "vegan",
      "vegetarian"
    ],
    "activeTime": 10,
    "passiveTime": 20,
    "totalTime": 30,
    "servings": 3,
    "difficulty": "easy",
    "originality": 4,
    "taste": 4,
    "status": "done",
    "source": "https://www.youtube.com/watch?v=p3HK5jzuQGo&t=124s&ab_channel=KaitlynTaylor",
    "ingredients": [
      {
        "name": "jasmine rice",
        "amount": 2,
        "unit": "cups"
      },
      {
        "name": "lime",
        "amount": 1,
        "unit": "pcs"
      },
      {
        "name": "water",
        "amount": 3,
        "unit": "cups"
      },
      {
        "name": "olive oil",
        "amount": 2,
        "unit": "tbsp"
      },
      {
        "name": "bay leaf",
        "amount": 1,
        "unit": "pcs"
      },
      {
        "name": "salt",
        "amount": 2,
        "unit": "tsp"
      },
      {
        "name": "cilantro (finely chopped)",
        "amount": 6,
        "unit": "tbsp"
      },
      {
        "name": "olive oil",
        "amount": 4,
        "unit": "tbsp"
      }
    ],
    "image": "https://ik.imagekit.io/o9fejv2tr/Food%20Images/MexicanCilantroRice.jpg?updatedAt=1762173721222",
    "file": "recipes/rice/MexicanCilantroRice.html"
  },
  {
    "title": "Seafood Paella",
    "categories": [
      "Spain",
      "rice",
      "seafood"
    ],
    "activeTime": 30,
    "passiveTime": 20,
    "totalTime": 50,
    "servings": 2,
    "difficulty": "easy",
    "originality": 5,
    "taste": 5,
    "status": "done",
    "source": "https://youtu.be/vNBuXsTY15E?si=dldkbQVomoKppRAV",
    "ingredients": [
      {
        "name": "garlic",
        "amount": 3,
        "unit": "cloves"
      },
      {
        "name": "onion",
        "amount": 0.5,
        "unit": "pcs"
      },
      {
        "name": "bellpepper",
        "amount": 0.5,
        "unit": "pcs"
      },
      {
        "name": "squid (head)",
        "amount": 1,
        "unit": "pcs"
      },
      {
        "name": "shrimp (peeled and deveined)",
        "amount": 12,
        "unit": "pcs"
      },
      {
        "name": "mussels",
        "amount": 8,
        "unit": "pcs"
      },
      {
        "name": "olive oil",
        "amount": 80,
        "unit": "ml"
      },
      {
        "name": "tomatoes (sieved)",
        "amount": 112,
        "unit": "g"
      },
      {
        "name": "paprika powder",
        "amount": 0.5,
        "unit": "tsp"
      },
      {
        "name": "fish broth",
        "amount": 600,
        "unit": "ml"
      },
      {
        "name": "saffron threads (or powder)",
        "amount": 0.25,
        "unit": "tsp"
      },
      {
        "name": "short-grain rice",
        "amount": 1,
        "unit": "cup"
      },
      {
        "name": "lemon wedges",
        "amount": 2,
        "unit": "pcs"
      },
      {
        "name": "parsley",
        "amount": 1,
        "unit": "handful"
      },
      {
        "name": "salt"
      },
      {
        "name": "pepper"
      }
    ],
    "image": "https://ik.imagekit.io/o9fejv2tr/Food%20Images/SeafoodPaella.jpg?updatedAt=1762175646182",
    "file": "recipes/rice/SeafoodPaella.html"
  },
  {
    "title": "Meatballs in mushroom gravy",
    "categories": [
      "Germany",
      "stew"
    ],
    "activeTime": 10,
    "passiveTime": 20,
    "totalTime": 30,
    "servings": 4,
    "difficulty": "easy",
    "originality": 4,
    "taste": 4,
    "status": "done",
    "source": "Mama",
    "ingredients": [
      {
        "name": "meatballs",
        "amount": 450,
        "unit": "g"
      },
      {
        "name": "onion",
        "amount": 1,
        "unit": "pcs"
      },
      {
        "name": "champignon",
        "amount": 500,
        "unit": "g"
      },
      {
        "name": "Schmorbraten-Powder",
        "amount": 1,
        "unit": "pack"
      },
      {
        "name": "butter",
        "amount": 1,
        "unit": "tbsp"
      },
      {
        "name": "water",
        "amount": 750,
        "unit": "ml"
      },
      {
        "name": "salt",
        "amount": 1,
        "unit": "tsp"
      },
      {
        "name": "chili powder (optional)"
      },
      {
        "name": "sugar",
        "amount": 0.5,
        "unit": "tsp"
      },
      {
        "name": "heavy cream",
        "amount": 200,
        "unit": "g"
      }
    ],
    "image": "https://ik.imagekit.io/o9fejv2tr/Food%20Images/MeatballsInMushroomGravy.jpg?updatedAt=1762177624440",
    "file": "recipes/dressings-dips-sauces/MeatballsInMushroomGravy.html"
  },
  {
    "title": "Japanese Curry",
    "categories": [
      "stew",
      "curry",
      "beef",
      "rice",
      "Japan"
    ],
    "activeTime": 30,
    "passiveTime": 45,
    "totalTime": 75,
    "servings": 3,
    "difficulty": "easy",
    "originality": 5,
    "taste": 5,
    "status": "done",
    "source": "https://www.youtube.com/watch?v=u5U-FH7o7v8&list=PLwXqhx9ZM-a_VsqCvTGJoXphf10mSI_Jf&index=163&ab_channel=Sudachi%7CJapaneseRecipes",
    "ingredients": [
      {
        "name": "onions",
        "amount": 300,
        "unit": "g"
      },
      {
        "name": "olive oil",
        "amount": 1,
        "unit": "tbsp"
      },
      {
        "name": "salt",
        "amount": 1,
        "unit": "pinch"
      },
      {
        "name": "water"
      },
      {
        "name": "beef",
        "amount": 300,
        "unit": "g"
      },
      {
        "name": "butter",
        "amount": 1,
        "unit": "tbsp"
      },
      {
        "name": "salt",
        "amount": 1,
        "unit": "pinch"
      },
      {
        "name": "garlic",
        "amount": 2,
        "unit": "cloves"
      },
      {
        "name": "carrots",
        "amount": 150,
        "unit": "g"
      },
      {
        "name": "potatoes",
        "amount": 200,
        "unit": "g"
      },
      {
        "name": "Japanese curry roux",
        "amount": 100,
        "unit": "g"
      },
      {
        "name": "water according to the roux package instructions",
        "amount": 90,
        "unit": "%"
      },
      {
        "name": "wine bases on the water amount from the roux package",
        "amount": 10,
        "unit": "%"
      },
      {
        "name": "instant coffee (optional)",
        "amount": 2,
        "unit": "tsp"
      }
    ],
    "image": "https://ik.imagekit.io/o9fejv2tr/Food%20Images/JapaneseCurry.jpg?updatedAt=1761480902593",
    "file": "recipes/rice/JapaneseCurry.html"
  },
  {
    "title": "Sushi",
    "categories": [
      "Japan",
      "rice",
      "snacks",
      "fingerfood"
    ],
    "activeTime": 5,
    "passiveTime": 50,
    "totalTime": 55,
    "servings": 4,
    "difficulty": "easy",
    "originality": 5,
    "taste": 5,
    "status": "done",
    "source": "https://youtu.be/X5PyhkwymNY?si=ElJxA0RQoGirlyAb",
    "ingredients": [
      {
        "name": "sushi rice",
        "amount": 300,
        "unit": "g"
      },
      {
        "name": "water (cold)",
        "amount": 350,
        "unit": "ml"
      },
      {
        "name": "kombu",
        "amount": 5,
        "unit": "g"
      },
      {
        "name": "sake",
        "amount": 1,
        "unit": "tbsp"
      },
      {
        "name": "rice vinegar",
        "amount": 2,
        "unit": "tbsp"
      },
      {
        "name": "sugar",
        "amount": 1,
        "unit": "tbsp"
      },
      {
        "name": "salt",
        "amount": 0.5,
        "unit": "tbsp"
      },
      {
        "name": "filling or toppings (e.g. cucumber, tuna, salmon, sesame,...)"
      },
      {
        "name": "nori sheets"
      }
    ],
    "image": "https://ik.imagekit.io/o9fejv2tr/Food%20Images/Sushi.jpg?updatedAt=1756588998692",
    "file": "recipes/snacks/Sushi.html"
  },
  {
    "title": "Gimbap",
    "categories": [
      "Korea",
      "snacks",
      "rice",
      "fingerfood"
    ],
    "activeTime": 40,
    "passiveTime": 10,
    "totalTime": 50,
    "servings": 4,
    "difficulty": "easy",
    "originality": 5,
    "taste": 4,
    "status": "done",
    "source": "https://youtu.be/Y-Y9CXGRJPU?si=QELC4MfHd1amjOQw",
    "ingredients": [
      {
        "name": "nori sheet",
        "amount": 5,
        "unit": "pcs"
      },
      {
        "name": "short-grain-rice",
        "amount": 2,
        "unit": "cups"
      },
      {
        "name": "sesame oil",
        "amount": 2,
        "unit": "tsp"
      },
      {
        "name": "salt",
        "amount": 0.5,
        "unit": "tsp"
      },
      {
        "name": "carrot (large)",
        "amount": 1,
        "unit": "pcs"
      },
      {
        "name": "salt",
        "amount": 1,
        "unit": "pinch"
      },
      {
        "name": "spinach",
        "amount": 250,
        "unit": "g"
      },
      {
        "name": "garlic",
        "amount": 2,
        "unit": "cloves"
      },
      {
        "name": "salt",
        "amount": 0.5,
        "unit": "tsp"
      },
      {
        "name": "sesame oil",
        "amount": 2,
        "unit": "tsp"
      },
      {
        "name": "ground beef",
        "amount": 230,
        "unit": "g"
      },
      {
        "name": "soy sauce",
        "amount": 2,
        "unit": "tsp"
      },
      {
        "name": "garlic",
        "amount": 1,
        "unit": "clove"
      },
      {
        "name": "pepper",
        "amount": 1,
        "unit": "pinch"
      },
      {
        "name": "brown sugar",
        "amount": 1,
        "unit": "tsp"
      },
      {
        "name": "egg",
        "amount": 3,
        "unit": "pcs"
      },
      {
        "name": "salt",
        "amount": 1,
        "unit": "pinch"
      },
      {
        "name": "pickled yellow radish (5 longs strips, 1cm thick)",
        "amount": 5,
        "unit": "pcs"
      }
    ],
    "image": "https://ik.imagekit.io/o9fejv2tr/Food%20Images/Gimbap.jpg?updatedAt=1756588882819",
    "file": "recipes/snacks/Gimbap.html"
  },
  {
    "title": "Cháo",
    "categories": [
      "Vietnam",
      "China",
      "rice",
      "chicken"
    ],
    "activeTime": 30,
    "passiveTime": 30,
    "totalTime": 60,
    "servings": 2,
    "difficulty": "easy",
    "originality": 5,
    "taste": 5,
    "status": "done",
    "source": "https://youtu.be/t2SahnNVULA?si=NsCA9_aTSGUrFPgr",
    "ingredients": [
      {
        "name": "rice",
        "amount": 1,
        "unit": "cup"
      },
      {
        "name": "water",
        "amount": 8,
        "unit": "cups"
      },
      {
        "name": "chicken breast",
        "amount": 300,
        "unit": "g"
      },
      {
        "name": "cornstarch",
        "amount": 2,
        "unit": "tsp"
      },
      {
        "name": "oyster sauce",
        "amount": 1,
        "unit": "tbsp"
      },
      {
        "name": "water",
        "amount": 2,
        "unit": "tbsp"
      },
      {
        "name": "chicken bouillon powder",
        "amount": 0.5,
        "unit": "tbsp"
      },
      {
        "name": "vegetable oil",
        "amount": 2,
        "unit": "tbsp"
      },
      {
        "name": "ginger (optional)",
        "amount": 14,
        "unit": "g"
      },
      {
        "name": "salt",
        "amount": 1,
        "unit": "tsp"
      },
      {
        "name": "chicken bouillon powder",
        "amount": 1,
        "unit": "tsp"
      },
      {
        "name": "spring onions (green part)"
      },
      {
        "name": "pepper"
      }
    ],
    "image": "https://ik.imagekit.io/o9fejv2tr/Food%20Images/Chao.jpg?updatedAt=1756588699668",
    "file": "recipes/rice/Chao.html"
  },
  {
    "title": "Pasta Cacio e Pepe",
    "categories": [
      "Italy",
      "noodles",
      "vegetarian"
    ],
    "activeTime": 18,
    "passiveTime": 12,
    "totalTime": 30,
    "servings": 2,
    "difficulty": "easy",
    "originality": 5,
    "taste": 4,
    "status": "done",
    "source": "https://youtu.be/Cx-KmIa-zco?si=Mo9Vgezt4Sa49qtR",
    "ingredients": [
      {
        "name": "spaghettoni",
        "amount": 300,
        "unit": "g"
      },
      {
        "name": "Pecorino Romano",
        "amount": 200,
        "unit": "g"
      },
      {
        "name": "pepper"
      },
      {
        "name": "rock salt"
      },
      {
        "name": "water",
        "amount": 3,
        "unit": "l"
      }
    ],
    "image": "https://ik.imagekit.io/o9fejv2tr/Food%20Images/CacioEPepe.jpg?updatedAt=1756588691716",
    "file": "recipes/noodle/CacioEPepe.html"
  },
  {
    "title": "Pasta Broccoli",
    "categories": [
      "Italy",
      "noodles",
      "vegetarian"
    ],
    "activeTime": 12,
    "passiveTime": 12,
    "totalTime": 24,
    "servings": 2,
    "difficulty": "easy",
    "originality": 5,
    "taste": 5,
    "status": "done",
    "source": "https://youtu.be/N3PFBKx-AH8?si=90UroUrQKlq_dyNs",
    "ingredients": [
      {
        "name": "broccoli",
        "amount": 1,
        "unit": "pcs"
      },
      {
        "name": "spaghetti",
        "amount": 300,
        "unit": "g"
      },
      {
        "name": "salt",
        "amount": 1,
        "unit": "tbsp"
      },
      {
        "name": "garlic",
        "amount": 2,
        "unit": "cloves"
      },
      {
        "name": "olive oil"
      },
      {
        "name": "Pecorino Romano"
      },
      {
        "name": "salt",
        "amount": 1,
        "unit": "pinch"
      },
      {
        "name": "pepper",
        "amount": 1,
        "unit": "pinch"
      }
    ],
    "image": "https://ik.imagekit.io/o9fejv2tr/Food%20Images/SpaghettiBroccoli.jpg?updatedAt=1756588994906",
    "file": "recipes/noodle/PastaBroccoli.html"
  },
  {
    "title": "Bean in syrup (for chè thập cẩm)",
    "categories": [
      "component",
      "vegan",
      "vegetarian"
    ],
    "activeTime": 2,
    "passiveTime": 8,
    "totalTime": 10,
    "servings": 8,
    "difficulty": "easy",
    "originality": 4,
    "taste": 4,
    "status": "need pic",
    "source": "https://youtu.be/xwq7TLbmqbs?si=FJfX6I7uPbrCJw7o",
    "ingredients": [
      {
        "name": "kidney bean (precooked)",
        "amount": 350,
        "unit": "g"
      },
      {
        "name": "water",
        "amount": 100,
        "unit": "ml"
      },
      {
        "name": "sugar",
        "amount": 50,
        "unit": "g"
      }
    ],
    "image": "https://ik.imagekit.io/o9fejv2tr/RecsWeb%20Icons/image_not_found.png?updatedAt=1756760226935",
    "file": "recipes/component/BeanInSyrup.html"
  },
  {
    "title": "Cook mung beans",
    "categories": [
      "component",
      "vegetarian",
      "vegan"
    ],
    "activeTime": 5,
    "passiveTime": 500,
    "totalTime": 505,
    "servings": 2,
    "difficulty": "easy",
    "originality": 5,
    "taste": 5,
    "status": "not done yet",
    "source": "https://youtu.be/Nw-BTahmx5M?si=_V_p-zLtgHH2GXvw",
    "ingredients": [
      {
        "name": "mung bean",
        "amount": 100,
        "unit": "g"
      },
      {
        "name": "salt",
        "amount": 0.5,
        "unit": "tsp"
      },
      {
        "name": "water",
        "amount": 400,
        "unit": "ml"
      }
    ],
    "image": "https://ik.imagekit.io/o9fejv2tr/RecsWeb%20Icons/image_not_found.png?updatedAt=1756760226935",
    "file": "recipes/component/CookMungBean.html"
  },
  {
    "title": "Mung Bean (for chè thập cẩm)",
    "categories": [
      "component",
      "vegetarian",
      "vegan"
    ],
    "activeTime": 2,
    "passiveTime": 0,
    "totalTime": 2,
    "servings": 6,
    "difficulty": "easy",
    "originality": 5,
    "taste": 4,
    "status": "not done yet",
    "source": "https://youtu.be/xwq7TLbmqbs?si=hMT9eaGEW97v5AJo",
    "ingredients": [
      {
        "name": "mung bean",
        "amount": 100,
        "unit": "g"
      },
      {
        "name": "salt",
        "amount": 0.3,
        "unit": "tsp"
      },
      {
        "name": "water",
        "amount": 400,
        "unit": "ml"
      },
      {
        "name": "water (boiled)",
        "amount": 100,
        "unit": "ml"
      },
      {
        "name": "sugar",
        "amount": 20,
        "unit": "g"
      },
      {
        "name": "vanilla sugar (alternatively 1 tsp vanilla extract)",
        "amount": 5,
        "unit": "g"
      }
    ],
    "image": "https://ik.imagekit.io/o9fejv2tr/RecsWeb%20Icons/image_not_found.png?updatedAt=1756760226935",
    "file": "recipes/component/MungBeanCheThapCam.html"
  },
  {
    "title": "Pasta Quattro Formaggi",
    "categories": [
      "Italy",
      "noodles",
      "vegetarian"
    ],
    "activeTime": 7,
    "passiveTime": 8,
    "totalTime": 15,
    "servings": 2,
    "difficulty": "easy",
    "originality": 5,
    "taste": 4,
    "status": "done",
    "source": "https://www.vincenzosplate.com/four-cheese-pasta/#wprm-recipe-video-container-13555",
    "ingredients": [
      {
        "name": "gorgonzola (alternatively blue cheese)",
        "amount": 50,
        "unit": "g"
      },
      {
        "name": "stracchino (alternatively ricotta or cottage cheese)",
        "amount": 50,
        "unit": "g"
      },
      {
        "name": "mascarpone",
        "amount": 50,
        "unit": "g"
      },
      {
        "name": "Pecorino Romano",
        "amount": 4,
        "unit": "tbsp"
      },
      {
        "name": "penne",
        "amount": 200,
        "unit": "g"
      },
      {
        "name": "whole milk",
        "amount": 80,
        "unit": "ml"
      },
      {
        "name": "salt",
        "amount": 1,
        "unit": "tbsp"
      },
      {
        "name": "walnuts (chopped)",
        "amount": 1,
        "unit": "handful"
      }
    ],
    "image": "https://ik.imagekit.io/o9fejv2tr/Food%20Images/QuattroFormaggi.jpg?updatedAt=1756588964588",
    "file": "recipes/noodle/PastaQuattroFormaggi.html"
  },
  {
    "title": "Pesto Alla Siciliana",
    "categories": [
      "Italy",
      "noodles",
      "vegetarian"
    ],
    "activeTime": 10,
    "passiveTime": 10,
    "totalTime": 10,
    "servings": 2,
    "difficulty": "easy",
    "originality": 5,
    "taste": 5,
    "status": "done",
    "source": "https://youtu.be/A4zE16mqrXg?si=nXH8ztuhOyMbClEy",
    "ingredients": [
      {
        "name": "pasta",
        "amount": 250,
        "unit": "g"
      },
      {
        "name": "cherry tomatoes",
        "amount": "8-10",
        "unit": "pcs"
      },
      {
        "name": "almonds (peeled)",
        "amount": 20,
        "unit": "pcs"
      },
      {
        "name": "basil leaves",
        "amount": 10,
        "unit": "pcs"
      },
      {
        "name": "garlic",
        "amount": 2,
        "unit": "cloves"
      },
      {
        "name": "pecorino (grated)",
        "amount": "20-30",
        "unit": "g"
      },
      {
        "name": "olive oil",
        "amount": 40,
        "unit": "ml"
      },
      {
        "name": "salt"
      },
      {
        "name": "pepper"
      }
    ],
    "image": "https://ik.imagekit.io/o9fejv2tr/Food%20Images/PestoAllaSicilliana.jpg?updatedAt=1756588957885",
    "file": "recipes/noodle/PestoAllaSiciliana.html"
  },
  {
    "title": "Pasta in cream and cheese Sauce",
    "categories": [
      "Italy",
      "noodles"
    ],
    "activeTime": 10,
    "passiveTime": 10,
    "totalTime": 20,
    "servings": 2,
    "difficulty": "easy",
    "originality": 5,
    "taste": 5,
    "status": "done",
    "source": "https://youtu.be/M3QxMEyK3mk?si=hxBCKBtvBEQREL1C",
    "ingredients": [
      {
        "name": "pasta",
        "amount": 250,
        "unit": "g"
      },
      {
        "name": "camembert",
        "amount": 1,
        "unit": "pcs"
      },
      {
        "name": "cream",
        "amount": 400,
        "unit": "ml"
      },
      {
        "name": "cooked ham",
        "amount": 120,
        "unit": "g"
      },
      {
        "name": "Parmesan"
      },
      {
        "name": "salt"
      },
      {
        "name": "pepper"
      }
    ],
    "image": "https://ik.imagekit.io/o9fejv2tr/Food%20Images/KaeseSahneSosse.jpg?updatedAt=1756588895929",
    "file": "recipes/noodle/PastaInCreamCheeseSauce.html"
  },
  {
    "title": "Babish’s Go-To Late-Night Pasta",
    "categories": [
      "Italy",
      "noodles",
      "vegetarian"
    ],
    "activeTime": 15,
    "passiveTime": 12,
    "totalTime": 27,
    "servings": 2,
    "difficulty": "easy",
    "originality": 5,
    "taste": 5,
    "status": "done",
    "source": "https://youtu.be/Tj26Na3q2d8?si=jpOnK2zWFJU-HtII",
    "ingredients": [
      {
        "name": "fussili",
        "amount": 200,
        "unit": "g"
      },
      {
        "name": "shallots",
        "amount": 2,
        "unit": "pcs"
      },
      {
        "name": "garlic",
        "amount": 4,
        "unit": "cloves"
      },
      {
        "name": "butter",
        "amount": 1,
        "unit": "tbsp"
      },
      {
        "name": "salt"
      },
      {
        "name": "pepper"
      },
      {
        "name": "olive oil"
      },
      {
        "name": "tomato paste",
        "amount": 2,
        "unit": "tbsp"
      },
      {
        "name": "cherry tomatoes",
        "amount": 250,
        "unit": "g"
      },
      {
        "name": "Mozzarella",
        "amount": 1,
        "unit": "pcs"
      },
      {
        "name": "Parmesan",
        "amount": 60,
        "unit": "g"
      },
      {
        "name": "basil"
      },
      {
        "name": "parsley",
        "amount": 0.5,
        "unit": "bunch"
      }
    ],
    "image": "https://ik.imagekit.io/o9fejv2tr/Food%20Images/BabishPasta.jpg?updatedAt=1756588648060",
    "file": "recipes/noodle/BabishsGoToLateNightPasta.html"
  },
  {
    "title": "Pilz-Rahmsauce",
    "categories": [
      "Germany",
      "sauce",
      "noodles",
      "vegetarian"
    ],
    "activeTime": 15,
    "passiveTime": 10,
    "totalTime": 25,
    "servings": 2,
    "difficulty": "easy",
    "originality": 5,
    "taste": 5,
    "status": "need pic",
    "source": "Familie Gherke",
    "ingredients": [
      {
        "name": "mushrooms",
        "amount": 250,
        "unit": "g"
      },
      {
        "name": "onion",
        "amount": 1,
        "unit": "pcs"
      },
      {
        "name": "cream",
        "amount": 400,
        "unit": "ml"
      },
      {
        "name": "salt",
        "amount": 1,
        "unit": "tsp"
      },
      {
        "name": "pepper",
        "amount": 0.5,
        "unit": "tsp"
      },
      {
        "name": "paprika powder",
        "amount": 0.5,
        "unit": "tsp"
      },
      {
        "name": "oil"
      },
      {
        "name": "cornstarch",
        "amount": 1,
        "unit": "tbsp"
      },
      {
        "name": "spring onions or chives (for garnish)"
      },
      {
        "name": "gnocchi",
        "amount": 800,
        "unit": "g"
      }
    ],
    "image": "https://ik.imagekit.io/o9fejv2tr/RecsWeb%20Icons/image_not_found.png?updatedAt=1756760226935",
    "file": "recipes/dressings-dips-sauces/PilzRahmsauce.html"
  },
  {
    "title": "Käsespätzle",
    "categories": [
      "Germany",
      "noodles",
      "vegetarian"
    ],
    "activeTime": 20,
    "passiveTime": 15,
    "totalTime": 35,
    "servings": 2,
    "difficulty": "easy",
    "originality": 5,
    "taste": 5,
    "status": "done",
    "source": "https://youtu.be/FfoN2hwWimE?si=HABgA1ZpgJ7YBIET",
    "ingredients": [
      {
        "name": "onion",
        "amount": 2,
        "unit": "pcs"
      },
      {
        "name": "spätzle",
        "amount": 500,
        "unit": "g"
      },
      {
        "name": "hard cheese (e.g. Tilsiter, Emmentaler, Appenzeller, Bergkäse,...)",
        "amount": 200,
        "unit": "g"
      },
      {
        "name": "salt"
      },
      {
        "name": "pepper"
      },
      {
        "name": "chives (chopped)",
        "amount": 3,
        "unit": "tbsp"
      },
      {
        "name": "butter"
      },
      {
        "name": "fried onions"
      }
    ],
    "image": "https://ik.imagekit.io/o9fejv2tr/Food%20Images/KaeseSpaetzle.jpg?updatedAt=1756588894989",
    "file": "recipes/noodle/Kaesespaetzle.html"
  },
  {
    "title": "Nudelsalat (classic)",
    "categories": [
      "Germany",
      "noodles",
      "salad"
    ],
    "activeTime": 30,
    "passiveTime": 70,
    "totalTime": 90,
    "servings": 6,
    "difficulty": "easy",
    "originality": 5,
    "taste": 5,
    "status": "done",
    "source": "https://youtu.be/L7McAjk7I1c?si=tFZWMRjVuAnYMpMJ",
    "ingredients": [
      {
        "name": "Hörnchennudeln",
        "amount": 400,
        "unit": "g"
      },
      {
        "name": "peas and carrots (canned)",
        "amount": 530,
        "unit": "g"
      },
      {
        "name": "pickles",
        "amount": "5-6",
        "unit": "pcs"
      },
      {
        "name": "Bologna sausage",
        "amount": 200,
        "unit": "g"
      },
      {
        "name": "Gouda",
        "amount": 150,
        "unit": "g"
      },
      {
        "name": "mayonnaise",
        "amount": 300,
        "unit": "g"
      },
      {
        "name": "pickle brine",
        "amount": 40,
        "unit": "ml"
      },
      {
        "name": "ketchup",
        "amount": 2,
        "unit": "tsp"
      },
      {
        "name": "salt"
      },
      {
        "name": "pepper"
      }
    ],
    "image": "https://ik.imagekit.io/o9fejv2tr/Food%20Images/Nudelsalat_klassisch.jpg?updatedAt=1756588945255",
    "file": "recipes/noodle/ClassicNudelsalat.html"
  },
  {
    "title": "Sommerlicher Nudelsalat",
    "categories": [
      "Germany",
      "noodles",
      "salad"
    ],
    "activeTime": 30,
    "passiveTime": 70,
    "totalTime": 90,
    "servings": 6,
    "difficulty": "easy",
    "originality": 5,
    "taste": 4,
    "status": "done",
    "source": "Jannis' Dad",
    "ingredients": [
      {
        "name": "Hörnchennudeln",
        "amount": 500,
        "unit": "g"
      },
      {
        "name": "tomatoes",
        "amount": 5,
        "unit": "pcs"
      },
      {
        "name": "bell pepper (red)",
        "amount": 3,
        "unit": "pcs"
      },
      {
        "name": "cucumber",
        "amount": 1,
        "unit": "pcs"
      },
      {
        "name": "onion (red)",
        "amount": 2,
        "unit": "pcs"
      },
      {
        "name": "bologna sausage",
        "amount": 1,
        "unit": "ring"
      },
      {
        "name": "sheep cheese",
        "amount": 1,
        "unit": "pck"
      },
      {
        "name": "corn",
        "amount": 285,
        "unit": "g"
      },
      {
        "name": "Miracle Whip",
        "amount": 500,
        "unit": "ml"
      },
      {
        "name": "Schmand",
        "amount": 1,
        "unit": "cup"
      },
      {
        "name": "balsamic vinegar (white)",
        "amount": 4,
        "unit": "tbsp"
      },
      {
        "name": "sugar",
        "amount": 1,
        "unit": "pinch"
      },
      {
        "name": "salt"
      },
      {
        "name": "pepper"
      },
      {
        "name": "parsley",
        "amount": 1,
        "unit": "bunch"
      }
    ],
    "image": "https://ik.imagekit.io/o9fejv2tr/Food%20Images/NudelsalatJannis.jpg?updatedAt=1756588945492",
    "file": "recipes/noodle/SommerlicherNudelsalat.html"
  },
  {
    "title": "Kartoffelpuffer/Reibekuchen",
    "categories": [
      "Germany",
      "potato",
      "streetfood",
      "snacks",
      "vegetarian",
      "vegan"
    ],
    "activeTime": 25,
    "passiveTime": 30,
    "totalTime": 55,
    "servings": 2,
    "difficulty": "easy",
    "originality": 5,
    "taste": 5,
    "status": "done",
    "source": "https://youtu.be/rODf39kwEys?si=6pwrWkETfm_sHNcQ",
    "ingredients": [
      {
        "name": "potatoes (waxy)",
        "amount": 500,
        "unit": "g"
      },
      {
        "name": "onion",
        "amount": 0.5,
        "unit": "pcs"
      },
      {
        "name": "nutmeg"
      },
      {
        "name": "salt"
      },
      {
        "name": "pepper"
      },
      {
        "name": "oil"
      }
    ],
    "image": "https://ik.imagekit.io/o9fejv2tr/Food%20Images/Kartoffelpuffer.jpg?updatedAt=1756588909567",
    "file": "recipes/potatoe/Kartoffelpuffer.html"
  },
  {
    "title": "Gratin dauphinois",
    "categories": [
      "France",
      "potato",
      "vegetarian"
    ],
    "activeTime": 50,
    "passiveTime": 75,
    "totalTime": 135,
    "servings": 3,
    "difficulty": "easy",
    "originality": 5,
    "taste": 5,
    "status": "done",
    "source": "https://youtu.be/gs429aLCMdE?si=ODSc3TYB7iYkKvep",
    "ingredients": [
      {
        "name": "potatoes (waxy)",
        "amount": 1.5,
        "unit": "kg"
      },
      {
        "name": "cream",
        "amount": 500,
        "unit": "ml"
      },
      {
        "name": "rosemary",
        "amount": 2,
        "unit": "sprigs"
      },
      {
        "name": "garlic",
        "amount": 2,
        "unit": "cloves"
      },
      {
        "name": "salt"
      },
      {
        "name": "pepper"
      },
      {
        "name": "nutmeg"
      },
      {
        "name": "Butter for greasing the baking dish"
      },
      {
        "name": "Parmesan",
        "amount": 50,
        "unit": "g"
      }
    ],
    "image": "https://ik.imagekit.io/o9fejv2tr/Food%20Images/Kartoffelgratin.jpg?updatedAt=1756588910983",
    "file": "recipes/potatoe/GratinDauphinois.html"
  },
  {
    "title": "Brötchen",
    "categories": [
      "Germany",
      "breads",
      "vegan",
      "vegetarian"
    ],
    "activeTime": 20,
    "passiveTime": 540,
    "totalTime": 560,
    "servings": 9,
    "difficulty": "easy",
    "originality": 5,
    "taste": 4,
    "status": "done",
    "source": "https://youtu.be/zCoTy0Tz4h8?si=sTd-jggpu-X-JJXt",
    "ingredients": [
      {
        "name": "spelt flour type 630 (alternatively wheat flour type 550)",
        "amount": 500,
        "unit": "g"
      },
      {
        "name": "cold water",
        "amount": 300,
        "unit": "g"
      },
      {
        "name": "olive oil",
        "amount": 20,
        "unit": "g"
      },
      {
        "name": "salt",
        "amount": 10,
        "unit": "g"
      },
      {
        "name": "Hefe (frisch, alternativ 0.5g trocken)",
        "amount": 1,
        "unit": "g"
      }
    ],
    "image": "https://ik.imagekit.io/o9fejv2tr/Food%20Images/Broetchen.jpg?updatedAt=1756588686855",
    "file": "recipes/breadAndBakedDishes/Broetchen.html"
  },
  {
    "title": "Flammkuchen",
    "categories": [
      "France",
      "Germany",
      "bakedDishes",
      "streetfood"
    ],
    "activeTime": 25,
    "passiveTime": 35,
    "totalTime": 60,
    "servings": 2,
    "difficulty": "easy",
    "originality": 5,
    "taste": 5,
    "status": "done",
    "source": "https://youtu.be/Pl13Atfzq-s?si=i3bxiIAeg4iJOsx4",
    "ingredients": [
      {
        "name": "flour (type 550)",
        "amount": 250,
        "unit": "g"
      },
      {
        "name": "water",
        "amount": 125,
        "unit": "ml"
      },
      {
        "name": "olive oil",
        "amount": 2,
        "unit": "tbsp"
      },
      {
        "name": "salt",
        "amount": 5,
        "unit": "g"
      },
      {
        "name": "crème fraîche",
        "amount": 250,
        "unit": "g"
      },
      {
        "name": "onion",
        "amount": 1,
        "unit": "pcs"
      },
      {
        "name": "bacon",
        "amount": 200,
        "unit": "g"
      },
      {
        "name": "spring onion"
      },
      {
        "name": "salt"
      },
      {
        "name": "pepper"
      }
    ],
    "image": "https://ik.imagekit.io/o9fejv2tr/Food%20Images/Flammkuchen.jpg?updatedAt=1756588836369",
    "file": "recipes/breadAndBakedDishes/Flammkuchen.html"
  },
  {
    "title": "Lángos",
    "categories": [
      "Hungary",
      "streetfood",
      "vegetarian"
    ],
    "activeTime": 40,
    "passiveTime": 85,
    "totalTime": 105,
    "servings": 6,
    "difficulty": "easy",
    "originality": 5,
    "taste": 4,
    "status": "done",
    "source": "https://youtu.be/hIgdBWdWvIc?si=eZ3PIt0cIbfXGMaa",
    "ingredients": [
      {
        "name": "garlic",
        "amount": "2-3",
        "unit": "cloves"
      },
      {
        "name": "oil",
        "amount": 50,
        "unit": "ml"
      },
      {
        "name": "water",
        "amount": 50,
        "unit": "ml"
      },
      {
        "name": "salt",
        "amount": 1,
        "unit": "tsp"
      },
      {
        "name": "flour",
        "amount": 500,
        "unit": "g"
      },
      {
        "name": "water (lukewarm)",
        "amount": 350,
        "unit": "ml"
      },
      {
        "name": "sugar",
        "amount": 2,
        "unit": "tsp"
      },
      {
        "name": "yeast (fresh)",
        "amount": 20,
        "unit": "g"
      },
      {
        "name": "salt",
        "amount": 1,
        "unit": "tbsp"
      },
      {
        "name": "oil",
        "amount": 100,
        "unit": "ml"
      },
      {
        "name": "oil for frying"
      },
      {
        "name": "Toppings: sour cream, cheese (cheddar, gouda),..."
      }
    ],
    "image": "https://ik.imagekit.io/o9fejv2tr/Food%20Images/Langos.jpg?updatedAt=1756588923878",
    "file": "recipes/streetfood/Langos.html"
  },
  {
    "title": "Canh Cá",
    "categories": [
      "Vietnam",
      "soup",
      "fish"
    ],
    "activeTime": 20,
    "passiveTime": 15,
    "totalTime": 35,
    "servings": 4,
    "difficulty": "easy",
    "originality": 5,
    "taste": 5,
    "status": "done",
    "source": "Mama",
    "ingredients": [
      {
        "name": "lemongrass",
        "amount": 1,
        "unit": "stalk"
      },
      {
        "name": "tomato",
        "amount": 1,
        "unit": "pcs"
      },
      {
        "name": "dracontomelon fruits",
        "amount": 2,
        "unit": "pcs"
      },
      {
        "name": "pineapple",
        "amount": "5-6",
        "unit": "pcs"
      },
      {
        "name": "garlic",
        "amount": 1,
        "unit": "clove"
      },
      {
        "name": "onion",
        "amount": 0.5,
        "unit": "pcs"
      },
      {
        "name": "salt",
        "amount": 1,
        "unit": "tsp"
      },
      {
        "name": "water",
        "amount": 750,
        "unit": "ml"
      },
      {
        "name": "fish",
        "amount": 300,
        "unit": "g"
      },
      {
        "name": "sugar",
        "amount": 0.5,
        "unit": "tsp"
      },
      {
        "name": "dill"
      }
    ],
    "image": "https://ik.imagekit.io/o9fejv2tr/Food%20Images/VietnameseFishSoup.jpg?updatedAt=1765195401077",
    "file": "recipes/soups/CanhCa.html"
  },
  {
    "title": "Chili con Carne",
    "categories": [
      "America",
      "stew",
      "beef"
    ],
    "activeTime": 20,
    "passiveTime": 65,
    "totalTime": 85,
    "servings": 3,
    "difficulty": "easy",
    "originality": 5,
    "taste": 5,
    "status": "done",
    "source": "https://youtu.be/5Do5f8b4cfY?feature=shared",
    "ingredients": [
      {
        "name": "ground beef",
        "amount": 500,
        "unit": "g"
      },
      {
        "name": "onions",
        "amount": 2,
        "unit": "pcs"
      },
      {
        "name": "garlic",
        "amount": 4,
        "unit": "cloves"
      },
      {
        "name": "chili",
        "amount": 1,
        "unit": "pcs"
      },
      {
        "name": "thai chili",
        "amount": 1,
        "unit": "pcs"
      },
      {
        "name": "tomatoes (peeled)",
        "amount": 2,
        "unit": "cans"
      },
      {
        "name": "kidney beans",
        "amount": 2,
        "unit": "small cans"
      },
      {
        "name": "vegetable broth",
        "amount": 300,
        "unit": "ml"
      },
      {
        "name": "tomato paste",
        "amount": 1.5,
        "unit": "tbsp"
      },
      {
        "name": "cinnamon",
        "amount": 1,
        "unit": "stick"
      },
      {
        "name": "paprika powder",
        "amount": 2,
        "unit": "tbsp"
      },
      {
        "name": "ground cumin",
        "amount": 0.5,
        "unit": "tsp"
      },
      {
        "name": "salt"
      },
      {
        "name": "pepper"
      },
      {
        "name": "corn (optional)"
      }
    ],
    "image": "https://ik.imagekit.io/o9fejv2tr/Food%20Images/ChiliConCarne.jpg?updatedAt=1756588718180",
    "file": "recipes/soups/ChiliConCarne.html"
  },
  {
    "title": "Bò hầm kiểu Pháp",
    "categories": [
      "Vietnam",
      "stew",
      "beef"
    ],
    "activeTime": 50,
    "passiveTime": 50,
    "totalTime": 100,
    "servings": 4,
    "difficulty": "easy",
    "originality": 5,
    "taste": 5,
    "status": "done",
    "source": "https://youtu.be/4X2ksdsF400?si=knRAdLthJsqzWmio",
    "ingredients": [
      {
        "name": "water",
        "amount": 500,
        "unit": "ml"
      },
      {
        "name": "salt",
        "amount": 1,
        "unit": "tsp"
      },
      {
        "name": "potatoes",
        "amount": 400,
        "unit": "g"
      },
      {
        "name": "carrots",
        "amount": 300,
        "unit": "g"
      },
      {
        "name": "celery",
        "amount": 2,
        "unit": "stalks"
      },
      {
        "name": "shallot",
        "amount": 15,
        "unit": "g"
      },
      {
        "name": "garlic",
        "amount": 40,
        "unit": "g"
      },
      {
        "name": "onion",
        "amount": 1,
        "unit": "pcs"
      },
      {
        "name": "parsley",
        "amount": 1,
        "unit": "handful"
      },
      {
        "name": "beef",
        "amount": 1,
        "unit": "kg"
      },
      {
        "name": "shimeji mashroom (alternatively champignon)",
        "amount": 100,
        "unit": "g"
      },
      {
        "name": "butter"
      },
      {
        "name": "chili sauce (e.g. Chin Su)",
        "amount": 2,
        "unit": "tbsp"
      },
      {
        "name": "strained tomatoes",
        "amount": 200,
        "unit": "g"
      },
      {
        "name": "oyster sauce",
        "amount": 3,
        "unit": "tbsp"
      },
      {
        "name": "red wine",
        "amount": 80,
        "unit": "ml"
      },
      {
        "name": "chicken stock powder",
        "amount": 1.5,
        "unit": "tbsp"
      },
      {
        "name": "garlic powder",
        "amount": 1,
        "unit": "tsp"
      },
      {
        "name": "sugar",
        "amount": 4,
        "unit": "tbsp"
      },
      {
        "name": "pepper",
        "amount": 1,
        "unit": "tsp"
      },
      {
        "name": "salt",
        "amount": 0.5,
        "unit": "tsp"
      },
      {
        "name": "water",
        "amount": 700,
        "unit": "ml"
      },
      {
        "name": "chili sauce",
        "amount": 1,
        "unit": "tbsp"
      },
      {
        "name": "butter",
        "amount": 10,
        "unit": "g"
      },
      {
        "name": "red wine",
        "amount": 40,
        "unit": "ml"
      }
    ],
    "image": "https://ik.imagekit.io/o9fejv2tr/Food%20Images/BoHamKieuPhap.jpg?updatedAt=1765198007545",
    "file": "recipes/soups/BoHamKieuPhap.html"
  },
  {
    "title": "Trứng tráng",
    "categories": [
      "Vietnam",
      "egg"
    ],
    "activeTime": 5,
    "passiveTime": 3,
    "totalTime": 8,
    "servings": 2,
    "difficulty": "easy",
    "originality": 5,
    "taste": 5,
    "status": "done",
    "source": "Mama",
    "ingredients": [
      {
        "name": "eggs",
        "amount": 3,
        "unit": "pcs"
      },
      {
        "name": "spring onion",
        "amount": 3,
        "unit": "stalks"
      },
      {
        "name": "fish sauce",
        "amount": 1,
        "unit": "tbsp"
      },
      {
        "name": "MSG"
      },
      {
        "name": "pepper"
      }
    ],
    "image": "https://ik.imagekit.io/o9fejv2tr/Food%20Images/TrungTrang.jpg?updatedAt=1765799663719",
    "file": "recipes/egg/TrungTrang.html"
  },
  {
    "title": "Eiersalat",
    "categories": [
      "Germany",
      "egg",
      "vegetarian"
    ],
    "activeTime": 10,
    "passiveTime": 190,
    "totalTime": 200,
    "servings": 4,
    "difficulty": "easy",
    "originality": 5,
    "taste": 5,
    "status": "done",
    "source": "https://www.gutekueche.at/klassischer-eiersalat-rezept-24947",
    "ingredients": [
      {
        "name": "eggs",
        "amount": 8,
        "unit": "pcs"
      },
      {
        "name": "mayonnaise",
        "amount": 2,
        "unit": "tbsp"
      },
      {
        "name": "salt",
        "amount": 1,
        "unit": "pinch"
      },
      {
        "name": "pepper",
        "amount": 1,
        "unit": "pinch"
      },
      {
        "name": "vinegar",
        "amount": 1,
        "unit": "tbsp"
      },
      {
        "name": "sour cream",
        "amount": 2,
        "unit": "tbsp"
      },
      {
        "name": "mustard",
        "amount": 0.5,
        "unit": "tbsp"
      },
      {
        "name": "chives",
        "amount": 1,
        "unit": "handful"
      }
    ],
    "image": "https://ik.imagekit.io/o9fejv2tr/Food%20Images/Eiersalat.jpg?updatedAt=1756588726115",
    "file": "recipes/egg/Eiersalat.html"
  },
  {
    "title": "Thịt Gián",
    "categories": [
      "Vietnam",
      "pork"
    ],
    "activeTime": 10,
    "passiveTime": 75,
    "totalTime": 85,
    "servings": 3,
    "difficulty": "easy",
    "originality": 5,
    "taste": 5,
    "status": "done",
    "source": "Mama",
    "ingredients": [
      {
        "name": "pork neck",
        "amount": 700,
        "unit": "g"
      },
      {
        "name": "onion",
        "amount": 0.5,
        "unit": "pcs"
      },
      {
        "name": "five-spice powder",
        "amount": 1,
        "unit": "tsp"
      },
      {
        "name": "fish sauce",
        "amount": 3,
        "unit": "tbsp"
      },
      {
        "name": "sugar",
        "amount": 1.5,
        "unit": "tbsp"
      },
      {
        "name": "pepper"
      },
      {
        "name": "salt",
        "amount": 1,
        "unit": "tsp"
      },
      {
        "name": "vegetable oil",
        "amount": 1,
        "unit": "tbsp"
      }
    ],
    "image": "https://ik.imagekit.io/o9fejv2tr/Food%20Images/ThitGian.jpg?updatedAt=1756588999750",
    "file": "recipes/pork/ThitGian.html"
  },
  {
    "title": "Pork in oyster sauce",
    "categories": [
      "Vietnam",
      "pork"
    ],
    "activeTime": 25,
    "passiveTime": 60,
    "totalTime": 85,
    "servings": 4,
    "difficulty": "easy",
    "originality": 5,
    "taste": 4,
    "status": "done",
    "source": "Mama",
    "ingredients": [
      {
        "name": "pork loin",
        "amount": 500,
        "unit": "g"
      },
      {
        "name": "oyster sauce",
        "amount": 3,
        "unit": "tbsp"
      },
      {
        "name": "fish sauce",
        "amount": 3,
        "unit": "tsp"
      },
      {
        "name": "sugar",
        "amount": 1,
        "unit": "heaped tsp"
      },
      {
        "name": "salt",
        "amount": 0.5,
        "unit": "tsp"
      },
      {
        "name": "soy sauce (dark)",
        "amount": 1,
        "unit": "tsp"
      },
      {
        "name": "onion",
        "amount": 1,
        "unit": "pcs"
      },
      {
        "name": "water",
        "amount": 1,
        "unit": "dash"
      }
    ],
    "image": "https://ik.imagekit.io/o9fejv2tr/Food%20Images/PorkInOysterSauce.jpg?updatedAt=1766530298584",
    "file": "recipes/pork/PorkInOysterSauce.html"
  },
  {
    "title": "Fried Vietnamese Pork Belly",
    "categories": [
      "Vietnam",
      "pork"
    ],
    "activeTime": 10,
    "passiveTime": 40,
    "totalTime": 50,
    "servings": 2,
    "difficulty": "easy",
    "originality": 5,
    "taste": 4,
    "status": "",
    "source": "Mama",
    "ingredients": [
      {
        "name": "pork belly",
        "amount": 500,
        "unit": "g"
      },
      {
        "name": "fish sauce",
        "amount": 3,
        "unit": "tbsp"
      },
      {
        "name": "pepper"
      },
      {
        "name": "water",
        "amount": "2-3",
        "unit": "tbsp"
      },
      {
        "name": "soy sauce (dark)",
        "amount": 0.5,
        "unit": "tsp"
      }
    ],
    "image": "https://ik.imagekit.io/o9fejv2tr/Food%20Images/FriedPorkBelly.jpg?updatedAt=1766530727615",
    "file": "recipes/pork/FriedPorkBelly.html"
  },
  {
    "title": "Thịt Kho Tàu",
    "categories": [
      "Vietnam",
      "pork"
    ],
    "activeTime": 30,
    "passiveTime": 180,
    "totalTime": 210,
    "servings": 2,
    "difficulty": "easy",
    "originality": 5,
    "taste": 5,
    "status": "done",
    "source": "N/A",
    "ingredients": [
      {
        "name": "eggs",
        "amount": 6,
        "unit": "pcs"
      },
      {
        "name": "pork belly",
        "amount": 400,
        "unit": "g"
      },
      {
        "name": "garlic",
        "amount": 1,
        "unit": "clove"
      },
      {
        "name": "sugar",
        "amount": 1,
        "unit": "tsp"
      },
      {
        "name": "chicken stock powder",
        "amount": 1,
        "unit": "tsp"
      },
      {
        "name": "fish sauce",
        "amount": 1,
        "unit": "tbsp"
      },
      {
        "name": "soy sauce (dark)",
        "amount": 1,
        "unit": "tsp"
      },
      {
        "name": "salt",
        "amount": 1,
        "unit": "tsp"
      },
      {
        "name": "garlic",
        "amount": 2,
        "unit": "cloves"
      },
      {
        "name": "onion",
        "amount": 0.5,
        "unit": "pcs"
      },
      {
        "name": "sugar",
        "amount": 2,
        "unit": "tsp"
      },
      {
        "name": "coconut water (optional)",
        "amount": "500-800",
        "unit": "ml"
      },
      {
        "name": "boiling water"
      },
      {
        "name": "Thai chili",
        "amount": 1,
        "unit": "pcs"
      }
    ],
    "image": "https://ik.imagekit.io/o9fejv2tr/Food%20Images/ThitKhoTau.jpg?updatedAt=1756589007940",
    "file": "recipes/pork/ThitKhoTau.html"
  }
]